mongodb_connect/__init__.py
mongodb_connect/mongo_crud.py
DBAutomation-0.0.3.dist-info/METADATA
DBAutomation-0.0.3.dist-info/WHEEL
DBAutomation-0.0.3.dist-info/top_level.txt
DBAutomation-0.0.3.dist-info/RECORD
