Metadata-Version: 2.1
Name: DBAutomation
Version: 0.0.3
Summary: A python package for connecting to database.
Home-page: https://github.com/Saurabh932/First-Mlops-MongoDb-Project
Author: Saurabh932
Author-email: saurabh.mandhalkar03@gmail.com
License: MIT
Classifier: Programming Language :: Python :: 3.8
Classifier: Programming Language :: Python :: 3.9
Classifier: Programming Language :: Python :: 3.10
Classifier: Operating System :: OS Independent
Provides-Extra: testing
Requires-Dist: pytest >=7.1.3 ; extra == 'testing'
Requires-Dist: mypy >=0.971 ; extra == 'testing'
Requires-Dist: flake8 >=5.0.4 ; extra == 'testing'
Requires-Dist: tox >=3.25.1 ; extra == 'testing'
Requires-Dist: black >=22.8.0 ; extra == 'testing'
